dax/XnatUtils.py
dax/__init__.py
dax/bin.py
dax/cluster.py
dax/dax_settings.py
dax/dax_tools_utils.py
dax/errors.py
dax/launcher.py
dax/log.py
dax/modules.py
dax/processors.py
dax/spiders.py
dax/task.py
dax/version.py
dax/xnat_tools_utils.py
dax/tests/__init__.py
dax/tests/test_dax.py
ldax-0.7.10.data/scripts/GenerateAutoSpider
ldax-0.7.10.data/scripts/GenerateModuleTemplate
ldax-0.7.10.data/scripts/GenerateProcessorTemplate
ldax-0.7.10.data/scripts/GenerateSettingsTemplate
ldax-0.7.10.data/scripts/GenerateSpiderTemplate
ldax-0.7.10.data/scripts/InitAutoSpider
ldax-0.7.10.data/scripts/Redcapreport
ldax-0.7.10.data/scripts/XnatCheckLogin
ldax-0.7.10.data/scripts/XnatCopyProject
ldax-0.7.10.data/scripts/XnatDemographic
ldax-0.7.10.data/scripts/XnatNDAR
ldax-0.7.10.data/scripts/XnatRandomSessionList
ldax-0.7.10.data/scripts/XnatSwitchProcessStatus
ldax-0.7.10.data/scripts/Xnatcheck
ldax-0.7.10.data/scripts/Xnatdelete
ldax-0.7.10.data/scripts/Xnatdl
ldax-0.7.10.data/scripts/Xnatdownload
ldax-0.7.10.data/scripts/Xnatinfo
ldax-0.7.10.data/scripts/Xnatmirror
ldax-0.7.10.data/scripts/Xnatquery
ldax-0.7.10.data/scripts/Xnatreport
ldax-0.7.10.data/scripts/Xnatsessionupdate
ldax-0.7.10.data/scripts/Xnatupload
ldax-0.7.10.data/scripts/dax
ldax-0.7.10.data/scripts/dax_build
ldax-0.7.10.data/scripts/dax_generator
ldax-0.7.10.data/scripts/dax_launch
ldax-0.7.10.data/scripts/dax_manager
ldax-0.7.10.data/scripts/dax_manager_hack_BLSA
ldax-0.7.10.data/scripts/dax_setup
ldax-0.7.10.data/scripts/dax_test
ldax-0.7.10.data/scripts/dax_update_tasks
ldax-0.7.10.data/scripts/dax_upload
ldax-0.7.10.data/scripts/fsdownload
ldax-0.7.10.data/scripts/fsupload
ldax-0.7.10.data/scripts/fsview
ldax-0.7.10.data/scripts/ldax_v2_setup.sh
ldax-0.7.10.data/scripts/run_spider
ldax-0.7.10.data/scripts/tracdownload
ldax-0.7.10.data/scripts/tracupload
ldax-0.7.10.data/scripts/tracview
ldax-0.7.10.dist-info/LICENSE
ldax-0.7.10.dist-info/METADATA
ldax-0.7.10.dist-info/WHEEL
ldax-0.7.10.dist-info/top_level.txt
ldax-0.7.10.dist-info/zip-safe
ldax-0.7.10.dist-info/RECORD
