Metadata-Version: 2.1
Name: ldax
Version: 0.7.10
Summary: Distributed Automation for XNAT
Home-page: http://github.com/VUIIS/LDax
Author: VUIIS CCI
Author-email: vuiis-cci@googlegroups.com
Maintainer: VUIIS CCI
Maintainer-email: vuiis-cci@googlegroups.com
License: MIT
Download-URL: http://github.com/VUIIS/LDax
Platform: MacOs
Platform: Linux
Classifier: Development Status :: 3 - Alpha
Classifier: Environment :: Console
Classifier: Intended Audience :: Science/Research
Classifier: Operating System :: MacOS :: MacOS X
Classifier: Operating System :: POSIX
Classifier: Operating System :: POSIX :: Linux
Classifier: Operating System :: Unix
Classifier: Programming Language :: Python :: 2.6
Classifier: Programming Language :: Python :: 2.7
Classifier: Programming Language :: Python :: 2 :: Only
Classifier: Topic :: Scientific/Engineering
Classifier: Topic :: Scientific/Engineering :: Information Analysis
Requires-Dist: alabaster (==0.7.12)
Requires-Dist: Babel (==2.8.0)
Requires-Dist: backports.functools-lru-cache (==1.4)
Requires-Dist: backports.shutil-get-terminal-size (==1.0.0)
Requires-Dist: bz2file (==0.98)
Requires-Dist: CacheControl-ldax (==0.12.5.3)
Requires-Dist: certifi (==2017.7.27.1)
Requires-Dist: chardet (==3.0.4)
Requires-Dist: configparser (==3.5.0)
Requires-Dist: cycler (==0.10.0)
Requires-Dist: decorator (==4.1.2)
Requires-Dist: docutils (==0.16)
Requires-Dist: enum34 (==1.1.6)
Requires-Dist: future (==0.16.0)
Requires-Dist: httpcache (==0.1.3)
Requires-Dist: httplib2 (==0.10.3)
Requires-Dist: idna (==2.6)
Requires-Dist: imagesize (==1.2.0)
Requires-Dist: ipython (==5.5.0)
Requires-Dist: ipython-genutils (==0.2.0)
Requires-Dist: Jinja2 (==2.11.1)
Requires-Dist: kiwisolver (==1.1.0)
Requires-Dist: lockfile (==0.12.2)
Requires-Dist: lxml (==4.1.0)
Requires-Dist: MarkupSafe (==1.1.1)
Requires-Dist: matplotlib (==2.1.0)
Requires-Dist: msgpack (==0.6.1)
Requires-Dist: nibabel (==2.2.0)
Requires-Dist: numpy (==1.13.3)
Requires-Dist: olefile (==0.44)
Requires-Dist: packaging (==20.1)
Requires-Dist: pandas (==0.21.0)
Requires-Dist: pathlib2 (==2.3.0)
Requires-Dist: pexpect (==4.3.0)
Requires-Dist: pickleshare (==0.7.4)
Requires-Dist: Pillow (==4.3.0)
Requires-Dist: prompt-toolkit (==1.0.15)
Requires-Dist: ptyprocess (==0.5.2)
Requires-Dist: PyCap (==1.0)
Requires-Dist: pydicom (==0.9.9)
Requires-Dist: Pygments (==2.2.0)
Requires-Dist: pyparsing (==2.2.0)
Requires-Dist: python-dateutil (==2.6.1)
Requires-Dist: pytz (==2017.3)
Requires-Dist: pyxnat-ldax (==1.0.0.0.7)
Requires-Dist: PyYAML (==3.12)
Requires-Dist: recon-stats-ldax (==0.0.4)
Requires-Dist: requests (==2.18.4)
Requires-Dist: requests-cache (==0.5.0)
Requires-Dist: scandir (==1.6)
Requires-Dist: scipy (==1.0.0)
Requires-Dist: semantic-version (==2.3.1)
Requires-Dist: simplegeneric (==0.8.1)
Requires-Dist: six (==1.11.0)
Requires-Dist: snowballstemmer (==2.0.0)
Requires-Dist: Sphinx (==1.8.5)
Requires-Dist: sphinxcontrib-websupport (==1.1.2)
Requires-Dist: subprocess32 (==3.2.7)
Requires-Dist: traitlets (==4.3.2)
Requires-Dist: typing (==3.7.4.1)
Requires-Dist: urllib3 (==1.22)
Requires-Dist: uuid (==1.30)
Requires-Dist: wcwidth (==0.1.7)
Requires-Dist: xlrd (==1.1.0)
